{
  "type": "crafting_shapeless",
  "ingredients": [
    {
      "item": "minecraft:bread"
    },
    {
      "item": "minecraft:brick_slab"
    },
    {
      "item": "minecraft:feather"
    },
    {
      "item": "minecraft:golden_leggings"
    },
    {
      "item": "minecraft:gray_carpet"
    },
    {
      "item": "minecraft:gray_concrete"
    },
    {
      "item": "minecraft:ladder"
    },
    {
      "item": "minecraft:pink_concrete"
    },
    {
      "item": "minecraft:red_mushroom"
    }
  ],
  "result": {
    "item": "minecraft:light_blue_concrete_powder",
    "count": 1
  }
}