{
  "effects": {
    "mood_sound": {
      "sound": "minecraft:ambient.cave",
      "tick_delay": 6000,
      "block_search_extent": 8,
      "offset": 2.0
    },
    "particle": {
      "options": {
        "type": "dripping_water"
      },
      "probability": 0.001
    },
    "foliage_color": 153,
    "grass_color": 102,
    "sky_color": 72,
    "fog_color": 102,
    "water_color": 54015,
    "water_fog_color": 13169151
  },
  "carvers": {},
  "features": [
    [],
    [],
    [],
    [],
    [],
    [],
    [],
    [],
    [],
    []
  ],
  "spawners": {
    "monster": [
      {
        "type": "creeper",
        "weight": 100,
        "minCount": 1,
        "maxCount": 1
      }
    ],
    "creature": [],
    "ambient": [],
    "water_creature": [],
    "water_ambient": [],
    "misc": []
  },
  "spawn_costs": {},
  "has_precipitation": false,
  "temperature": 0.5,
  "downfall": 0.5
}