{
  "pools": [
    {
      "rolls": 1,
      "entries": [
        {
          "Weight": 1,
          "type": "loot_table",
          "name": "item:item/carrot_on_a_stick/void_bundle"
        },
        {
          "Weight": 1,
          "type": "loot_table",
          "name": "item:item/carrot_on_a_stick/golden_ticket_knight"
        },
        {
          "Weight": 1,
          "type": "loot_table",
          "name": "item:item/carrot_on_a_stick/golden_ticket_ninja"
        },
        {
          "Weight": 1,
          "type": "loot_table",
          "name": "item:item/carrot_on_a_stick/golden_ticket_hunter"
        },
        {
          "Weight": 1,
          "type": "loot_table",
          "name": "item:item/carrot_on_a_stick/golden_ticket_white_mage"
        },
        {
          "Weight": 1,
          "type": "loot_table",
          "name": "item:item/carrot_on_a_stick/golden_ticket_black_mage"
        },
        {
          "Weight": 1,
          "type": "loot_table",
          "name": "item:item/carrot_on_a_stick/golden_ticket_summoner"
        },
        {
          "Weight": 1,
          "type": "loot_table",
          "name": "item:item/carrot_on_a_stick/golden_ticket_puppet_master"
        },
        {
          "Weight": 1,
          "type": "loot_table",
          "name": "item:item/carrot_on_a_stick/golden_ticket_phantom_thief"
        },
        {
          "Weight": 1,
          "type": "loot_table",
          "name": "item:item/emerald/currency_megaton_emerald"
        },
        {
          "Weight": 1,
          "type": "loot_table",
          "name": "item:item/emerald/currency_gigant_emerald"
        },
        {
          "Weight": 1,
          "type": "loot_table",
          "name": "item:item/emerald/currency_void"
        },
        {
          "Weight": 1,
          "type": "loot_table",
          "name": "item:item/fishing_rod/cthulure"
        },
        {
          "Weight": 1,
          "type": "loot_table",
          "name": "item:item/fishing_rod/legendary_fishing_rod"
        },
        {
          "Weight": 1,
          "type": "loot_table",
          "name": "item:item/gold_nugget/mystery/5"
        },
        {
          "Weight": 1,
          "type": "loot_table",
          "name": "item:item/gold_nugget/mystery/6"
        },
        {
          "Weight": 1,
          "type": "loot_table",
          "name": "item:item/gold_nugget/mystery/7"
        },
        {
          "Weight": 1,
          "type": "loot_table",
          "name": "item:item/gold_nugget/mystery/8"
        },
        {
          "Weight": 1,
          "type": "loot_table",
          "name": "item:item/gold_nugget/blade/5"
        },
        {
          "Weight": 1,
          "type": "loot_table",
          "name": "item:item/gold_nugget/blade/6"
        },
        {
          "Weight": 1,
          "type": "loot_table",
          "name": "item:item/gold_nugget/blade/7"
        },
        {
          "Weight": 1,
          "type": "loot_table",
          "name": "item:item/gold_nugget/blade/8"
        },
        {
          "Weight": 1,
          "type": "loot_table",
          "name": "item:item/gold_nugget/add_fire/5"
        },
        {
          "Weight": 1,
          "type": "loot_table",
          "name": "item:item/gold_nugget/add_fire/6"
        },
        {
          "Weight": 1,
          "type": "loot_table",
          "name": "item:item/gold_nugget/add_fire/7"
        },
        {
          "Weight": 1,
          "type": "loot_table",
          "name": "item:item/gold_nugget/add_fire/8"
        },
        {
          "Weight": 1,
          "type": "loot_table",
          "name": "item:item/gold_nugget/add_ice/5"
        },
        {
          "Weight": 1,
          "type": "loot_table",
          "name": "item:item/gold_nugget/add_ice/6"
        },
        {
          "Weight": 1,
          "type": "loot_table",
          "name": "item:item/gold_nugget/add_ice/7"
        },
        {
          "Weight": 1,
          "type": "loot_table",
          "name": "item:item/gold_nugget/add_ice/8"
        },
        {
          "Weight": 1,
          "type": "loot_table",
          "name": "item:item/gold_nugget/add_lightning/5"
        },
        {
          "Weight": 1,
          "type": "loot_table",
          "name": "item:item/gold_nugget/add_lightning/6"
        },
        {
          "Weight": 1,
          "type": "loot_table",
          "name": "item:item/gold_nugget/add_lightning/7"
        },
        {
          "Weight": 1,
          "type": "loot_table",
          "name": "item:item/gold_nugget/add_lightning/8"
        },
        {
          "Weight": 1,
          "type": "loot_table",
          "name": "item:item/gold_nugget/add_light/5"
        },
        {
          "Weight": 1,
          "type": "loot_table",
          "name": "item:item/gold_nugget/add_light/6"
        },
        {
          "Weight": 1,
          "type": "loot_table",
          "name": "item:item/gold_nugget/add_light/7"
        },
        {
          "Weight": 1,
          "type": "loot_table",
          "name": "item:item/gold_nugget/add_light/8"
        },
        {
          "Weight": 1,
          "type": "loot_table",
          "name": "item:item/gold_nugget/add_dark/5"
        },
        {
          "Weight": 1,
          "type": "loot_table",
          "name": "item:item/gold_nugget/add_dark/6"
        },
        {
          "Weight": 1,
          "type": "loot_table",
          "name": "item:item/gold_nugget/add_dark/7"
        },
        {
          "Weight": 1,
          "type": "loot_table",
          "name": "item:item/gold_nugget/add_dark/8"
        },
        {
          "Weight": 1,
          "type": "loot_table",
          "name": "item:item/gold_nugget/element/5"
        },
        {
          "Weight": 1,
          "type": "loot_table",
          "name": "item:item/gold_nugget/element/6"
        },
        {
          "Weight": 1,
          "type": "loot_table",
          "name": "item:item/gold_nugget/element/7"
        },
        {
          "Weight": 1,
          "type": "loot_table",
          "name": "item:item/gold_nugget/element/8"
        },
        {
          "Weight": 1,
          "type": "loot_table",
          "name": "item:item/gold_nugget/yin_yang/5"
        },
        {
          "Weight": 1,
          "type": "loot_table",
          "name": "item:item/gold_nugget/yin_yang/6"
        },
        {
          "Weight": 1,
          "type": "loot_table",
          "name": "item:item/gold_nugget/yin_yang/7"
        },
        {
          "Weight": 1,
          "type": "loot_table",
          "name": "item:item/gold_nugget/yin_yang/8"
        },
        {
          "Weight": 1,
          "type": "loot_table",
          "name": "item:item/gold_nugget/spirit/1"
        },
        {
          "Weight": 1,
          "type": "loot_table",
          "name": "item:item/gold_nugget/spirit/3"
        },
        {
          "Weight": 1,
          "type": "loot_table",
          "name": "item:item/gold_nugget/spirit/4"
        },
        {
          "Weight": 1,
          "type": "loot_table",
          "name": "item:item/gold_nugget/spirit/5"
        },
        {
          "Weight": 1,
          "type": "loot_table",
          "name": "item:item/gold_nugget/spirit/6"
        },
        {
          "Weight": 1,
          "type": "loot_table",
          "name": "item:item/gold_nugget/spirit/7"
        },
        {
          "Weight": 1,
          "type": "loot_table",
          "name": "item:item/gold_nugget/spirit/8"
        },
        {
          "Weight": 1,
          "type": "loot_table",
          "name": "item:item/gold_nugget/boost_fire/5"
        },
        {
          "Weight": 1,
          "type": "loot_table",
          "name": "item:item/gold_nugget/boost_fire/6"
        },
        {
          "Weight": 1,
          "type": "loot_table",
          "name": "item:item/gold_nugget/boost_fire/7"
        },
        {
          "Weight": 1,
          "type": "loot_table",
          "name": "item:item/gold_nugget/boost_fire/8"
        },
        {
          "Weight": 1,
          "type": "loot_table",
          "name": "item:item/gold_nugget/boost_ice/5"
        },
        {
          "Weight": 1,
          "type": "loot_table",
          "name": "item:item/gold_nugget/boost_ice/6"
        },
        {
          "Weight": 1,
          "type": "loot_table",
          "name": "item:item/gold_nugget/boost_ice/7"
        },
        {
          "Weight": 1,
          "type": "loot_table",
          "name": "item:item/gold_nugget/boost_ice/8"
        },
        {
          "Weight": 1,
          "type": "loot_table",
          "name": "item:item/gold_nugget/boost_lightning/5"
        },
        {
          "Weight": 1,
          "type": "loot_table",
          "name": "item:item/gold_nugget/boost_lightning/6"
        },
        {
          "Weight": 1,
          "type": "loot_table",
          "name": "item:item/gold_nugget/boost_lightning/7"
        },
        {
          "Weight": 1,
          "type": "loot_table",
          "name": "item:item/gold_nugget/boost_lightning/8"
        },
        {
          "Weight": 1,
          "type": "loot_table",
          "name": "item:item/gold_nugget/boost_light/5"
        },
        {
          "Weight": 1,
          "type": "loot_table",
          "name": "item:item/gold_nugget/boost_light/6"
        },
        {
          "Weight": 1,
          "type": "loot_table",
          "name": "item:item/gold_nugget/boost_light/7"
        },
        {
          "Weight": 1,
          "type": "loot_table",
          "name": "item:item/gold_nugget/boost_light/8"
        },
        {
          "Weight": 1,
          "type": "loot_table",
          "name": "item:item/gold_nugget/boost_dark/5"
        },
        {
          "Weight": 1,
          "type": "loot_table",
          "name": "item:item/gold_nugget/boost_dark/6"
        },
        {
          "Weight": 1,
          "type": "loot_table",
          "name": "item:item/gold_nugget/boost_dark/7"
        },
        {
          "Weight": 1,
          "type": "loot_table",
          "name": "item:item/gold_nugget/boost_dark/8"
        },
        {
          "Weight": 1,
          "type": "loot_table",
          "name": "item:item/gold_nugget/philosopher/5"
        },
        {
          "Weight": 1,
          "type": "loot_table",
          "name": "item:item/gold_nugget/philosopher/6"
        },
        {
          "Weight": 1,
          "type": "loot_table",
          "name": "item:item/gold_nugget/philosopher/7"
        },
        {
          "Weight": 1,
          "type": "loot_table",
          "name": "item:item/gold_nugget/philosopher/8"
        },
        {
          "Weight": 1,
          "type": "loot_table",
          "name": "item:item/gold_nugget/purification/5"
        },
        {
          "Weight": 1,
          "type": "loot_table",
          "name": "item:item/gold_nugget/purification/6"
        },
        {
          "Weight": 1,
          "type": "loot_table",
          "name": "item:item/gold_nugget/purification/7"
        },
        {
          "Weight": 1,
          "type": "loot_table",
          "name": "item:item/gold_nugget/purification/8"
        },
        {
          "Weight": 1,
          "type": "loot_table",
          "name": "item:item/gold_nugget/kamui/1"
        },
        {
          "Weight": 1,
          "type": "loot_table",
          "name": "item:item/gold_nugget/kamui/3"
        },
        {
          "Weight": 1,
          "type": "loot_table",
          "name": "item:item/gold_nugget/kamui/4"
        },
        {
          "Weight": 1,
          "type": "loot_table",
          "name": "item:item/gold_nugget/kamui/5"
        },
        {
          "Weight": 1,
          "type": "loot_table",
          "name": "item:item/gold_nugget/kamui/6"
        },
        {
          "Weight": 1,
          "type": "loot_table",
          "name": "item:item/gold_nugget/kamui/7"
        },
        {
          "Weight": 1,
          "type": "loot_table",
          "name": "item:item/gold_nugget/kamui/8"
        },
        {
          "Weight": 1,
          "type": "loot_table",
          "name": "item:item/gold_nugget/mystic/1"
        },
        {
          "Weight": 1,
          "type": "loot_table",
          "name": "item:item/gold_nugget/mystic/2"
        },
        {
          "Weight": 1,
          "type": "loot_table",
          "name": "item:item/gold_nugget/mystic/3"
        },
        {
          "Weight": 1,
          "type": "loot_table",
          "name": "item:item/gold_nugget/mystic/4"
        },
        {
          "Weight": 1,
          "type": "loot_table",
          "name": "item:item/gold_nugget/mystic/5"
        },
        {
          "Weight": 1,
          "type": "loot_table",
          "name": "item:item/gold_nugget/mystic/6"
        },
        {
          "Weight": 1,
          "type": "loot_table",
          "name": "item:item/gold_nugget/mystic/7"
        },
        {
          "Weight": 1,
          "type": "loot_table",
          "name": "item:item/gold_nugget/mystic/8"
        },
        {
          "Weight": 1,
          "type": "loot_table",
          "name": "item:item/gold_nugget/knockback/5"
        },
        {
          "Weight": 1,
          "type": "loot_table",
          "name": "item:item/gold_nugget/knockback/6"
        },
        {
          "Weight": 1,
          "type": "loot_table",
          "name": "item:item/gold_nugget/knockback/7"
        },
        {
          "Weight": 1,
          "type": "loot_table",
          "name": "item:item/gold_nugget/knockback/8"
        },
        {
          "Weight": 1,
          "type": "loot_table",
          "name": "item:item/gold_nugget/protection/5"
        },
        {
          "Weight": 1,
          "type": "loot_table",
          "name": "item:item/gold_nugget/protection/6"
        },
        {
          "Weight": 1,
          "type": "loot_table",
          "name": "item:item/gold_nugget/protection/7"
        },
        {
          "Weight": 1,
          "type": "loot_table",
          "name": "item:item/gold_nugget/protection/8"
        },
        {
          "Weight": 1,
          "type": "loot_table",
          "name": "item:item/gold_nugget/projectile_protection/5"
        },
        {
          "Weight": 1,
          "type": "loot_table",
          "name": "item:item/gold_nugget/projectile_protection/6"
        },
        {
          "Weight": 1,
          "type": "loot_table",
          "name": "item:item/gold_nugget/projectile_protection/7"
        },
        {
          "Weight": 1,
          "type": "loot_table",
          "name": "item:item/gold_nugget/projectile_protection/8"
        },
        {
          "Weight": 1,
          "type": "loot_table",
          "name": "item:item/gold_nugget/blast_protection/5"
        },
        {
          "Weight": 1,
          "type": "loot_table",
          "name": "item:item/gold_nugget/blast_protection/6"
        },
        {
          "Weight": 1,
          "type": "loot_table",
          "name": "item:item/gold_nugget/blast_protection/7"
        },
        {
          "Weight": 1,
          "type": "loot_table",
          "name": "item:item/gold_nugget/blast_protection/8"
        },
        {
          "Weight": 1,
          "type": "loot_table",
          "name": "item:item/gold_nugget/fire_protection/5"
        },
        {
          "Weight": 1,
          "type": "loot_table",
          "name": "item:item/gold_nugget/fire_protection/6"
        },
        {
          "Weight": 1,
          "type": "loot_table",
          "name": "item:item/gold_nugget/fire_protection/7"
        },
        {
          "Weight": 1,
          "type": "loot_table",
          "name": "item:item/gold_nugget/fire_protection/8"
        },
        {
          "Weight": 1,
          "type": "loot_table",
          "name": "item:item/gold_nugget/feather_falling/5"
        },
        {
          "Weight": 1,
          "type": "loot_table",
          "name": "item:item/gold_nugget/feather_falling/6"
        },
        {
          "Weight": 1,
          "type": "loot_table",
          "name": "item:item/gold_nugget/feather_falling/7"
        },
        {
          "Weight": 1,
          "type": "loot_table",
          "name": "item:item/gold_nugget/feather_falling/8"
        },
        {
          "Weight": 1,
          "type": "loot_table",
          "name": "item:item/gold_nugget/dragon_scale/5"
        },
        {
          "Weight": 1,
          "type": "loot_table",
          "name": "item:item/gold_nugget/dragon_scale/6"
        },
        {
          "Weight": 1,
          "type": "loot_table",
          "name": "item:item/gold_nugget/dragon_scale/7"
        },
        {
          "Weight": 1,
          "type": "loot_table",
          "name": "item:item/gold_nugget/dragon_scale/8"
        },
        {
          "Weight": 1,
          "type": "loot_table",
          "name": "item:item/gold_nugget/life/5"
        },
        {
          "Weight": 1,
          "type": "loot_table",
          "name": "item:item/gold_nugget/life/6"
        },
        {
          "Weight": 1,
          "type": "loot_table",
          "name": "item:item/gold_nugget/life/7"
        },
        {
          "Weight": 1,
          "type": "loot_table",
          "name": "item:item/gold_nugget/life/8"
        },
        {
          "Weight": 1,
          "type": "loot_table",
          "name": "item:item/gold_nugget/mana/5"
        },
        {
          "Weight": 1,
          "type": "loot_table",
          "name": "item:item/gold_nugget/mana/6"
        },
        {
          "Weight": 1,
          "type": "loot_table",
          "name": "item:item/gold_nugget/mana/7"
        },
        {
          "Weight": 1,
          "type": "loot_table",
          "name": "item:item/gold_nugget/mana/8"
        },
        {
          "Weight": 1,
          "type": "loot_table",
          "name": "item:item/gold_nugget/evolution/5"
        },
        {
          "Weight": 1,
          "type": "loot_table",
          "name": "item:item/gold_nugget/evolution/6"
        },
        {
          "Weight": 1,
          "type": "loot_table",
          "name": "item:item/gold_nugget/evolution/7"
        },
        {
          "Weight": 1,
          "type": "loot_table",
          "name": "item:item/gold_nugget/evolution/8"
        },
        {
          "Weight": 1,
          "type": "loot_table",
          "name": "item:item/gold_nugget/wave_of_element/5"
        },
        {
          "Weight": 1,
          "type": "loot_table",
          "name": "item:item/gold_nugget/wave_of_element/6"
        },
        {
          "Weight": 1,
          "type": "loot_table",
          "name": "item:item/gold_nugget/wave_of_element/7"
        },
        {
          "Weight": 1,
          "type": "loot_table",
          "name": "item:item/gold_nugget/wave_of_element/8"
        },
        {
          "Weight": 1,
          "type": "loot_table",
          "name": "item:item/gold_nugget/double_break/5"
        },
        {
          "Weight": 1,
          "type": "loot_table",
          "name": "item:item/gold_nugget/double_break/6"
        },
        {
          "Weight": 1,
          "type": "loot_table",
          "name": "item:item/gold_nugget/double_break/7"
        },
        {
          "Weight": 1,
          "type": "loot_table",
          "name": "item:item/gold_nugget/double_break/8"
        },
        {
          "Weight": 1,
          "type": "loot_table",
          "name": "item:item/iron_pickaxe/jewel_mining"
        },
        {
          "Weight": 1,
          "type": "loot_table",
          "name": "item:item/player_head/knight_head"
        },
        {
          "Weight": 1,
          "type": "loot_table",
          "name": "item:item/player_head/ninja_head"
        },
        {
          "Weight": 1,
          "type": "loot_table",
          "name": "item:item/player_head/hunter_head"
        },
        {
          "Weight": 1,
          "type": "loot_table",
          "name": "item:item/player_head/white_mage_head"
        },
        {
          "Weight": 1,
          "type": "loot_table",
          "name": "item:item/player_head/black_mage_head"
        },
        {
          "Weight": 1,
          "type": "loot_table",
          "name": "item:item/player_head/summoner_head"
        },
        {
          "Weight": 1,
          "type": "loot_table",
          "name": "item:item/warped_fungus_on_a_stick/pyramid_head"
        },
        {
          "Weight": 1,
          "type": "loot_table",
          "name": "item:item/warped_fungus_on_a_stick/security_pole/security_pole_single_body"
        },
        {
          "Weight": 1,
          "type": "loot_table",
          "name": "item:item/warped_fungus_on_a_stick/security_pole/security_pole_dual_body"
        },
        {
          "Weight": 1,
          "type": "loot_table",
          "name": "item:item/warped_fungus_on_a_stick/security_pole/security_pole_triple_body"
        },
        {
          "Weight": 1,
          "type": "loot_table",
          "name": "item:item/warped_fungus_on_a_stick/block/portal"
        }
      ]
    }
  ]
}