{
  "display": {
    "icon": {
      "item": "minecraft:yellow_stained_glass"
    },
    "title": {
      "text": "封印を解くカギ"
    },
    "description": {
      "text": "ガリバーランドの攻略には、封印を解くカギが不可欠"
    },
    "frame": "task",
    "show_toast": true,
    "announce_to_chat": true,
    "hidden": false
  },
  "parent": "advancement_manager:gullivers_land/root",
  "criteria": {
    "key_red": {
      "trigger": "minecraft:inventory_changed",
      "conditions": {
        "items": [
          {
            "item": "minecraft:armor_stand",
            "nbt": "{display:{Name:\"\\\"A\\\"\"}}"
          }
        ]
      }
    },
    "key_yellow": {
      "trigger": "minecraft:inventory_changed",
      "conditions": {
        "items": [
          {
            "item": "minecraft:armor_stand",
            "nbt": "{display:{Name:\"\\\"B\\\"\"}}"
          }
        ]
      }
    },
    "key_blue": {
      "trigger": "minecraft:inventory_changed",
      "conditions": {
        "items": [
          {
            "item": "minecraft:armor_stand",
            "nbt": "{display:{Name:\"\\\"C\\\"\"}}"
          }
        ]
      }
    }
  },
  "requirements": [
    [
      "key_red",
      "key_yellow",
      "key_blue"
    ]
  ]
}