{
  "pools": [
    {
      "rolls": 1,
      "entries": [
        {
          "type": "minecraft:item",
          "name": "minecraft:paper",
          "functions": [
            {
              "function": "minecraft:set_nbt",
              "tag": "{CustomModelData:6,JobChangeTo:6,display:{Name:'[\"\",{\"text\":\"S \",\"color\":\"green\",\"font\":\"icon\"},{\"translate\":\"\u53ec\u559a\u58eb\u5909\u66f4\u7533\u8acb\u66f8\",\"bold\":true}]',Lore:['{\"translate\":\"\u50d5\u3068\u5951\u7d04\u3057\u3066\u53ec\u559a\u58eb\u306b\u306a\u3063\u3066\u3088\",\"color\":\"yellow\"}','{\"translate\":\"USB\u8077\u696d\u5b89\u5b9a\u6240\"}']}}"
            }
          ]
        }
      ]
    }
  ]
}