{
  "type": "crafting_shapeless",
  "ingredients": [
    {
      "item": "minecraft:blue_terracotta"
    },
    {
      "item": "minecraft:dragon_head"
    },
    {
      "item": "minecraft:green_stained_glass"
    },
    {
      "item": "minecraft:horn_coral_fan"
    },
    {
      "item": "minecraft:iron_block"
    },
    {
      "item": "minecraft:jungle_leaves"
    },
    {
      "item": "minecraft:purpur_stairs"
    },
    {
      "item": "minecraft:rose_red"
    },
    {
      "item": "minecraft:sand"
    }
  ],
  "result": {
    "item": "minecraft:pink_concrete_powder",
    "count": 1
  }
}