{
  "display": {
    "icon": {
      "item": "minecraft:end_crystal"
    },
    "title": {
      "text": "水面に映る星"
    },
    "description": {
      "text": "熟練の釣り人であれば、水面に映る星すらも釣れると言う"
    },
    "frame": "challenge",
    "show_toast": true,
    "announce_to_chat": true,
    "hidden": false
  },
  "parent": "advancement_manager:skill_setting_field/fishing_ticket",
  "criteria": {
    "ticket": {
      "trigger": "minecraft:inventory_changed",
      "conditions": {
        "items": [
          {
            "item": "minecraft:end_crystal",
            "nbt": "{}"
          }
        ]
      }
    }
  }
}