{
  "type": "crafting_shapeless",
  "ingredients": [
    {
      "item": "minecraft:diamond_leggings"
    },
    {
      "item": "minecraft:enchanted_book"
    },
    {
      "item": "minecraft:glass_bottle"
    },
    {
      "item": "minecraft:iron_ingot"
    },
    {
      "item": "minecraft:kelp"
    },
    {
      "item": "minecraft:magma_cream"
    },
    {
      "item": "minecraft:nether_brick_slab"
    },
    {
      "item": "minecraft:pink_wool"
    },
    {
      "item": "minecraft:prismarine_brick_slab"
    }
  ],
  "result": {
    "item": "minecraft:brown_concrete_powder",
    "count": 1
  }
}