{
  "condition": "minecraft:alternative",
  "terms": [
    {
      "condition": "minecraft:entity_properties",
      "entity": "this",
      "predicate": {
        "equipment": {
          "mainhand": {
            "item": "minecraft:wooden_sword"
          }
        }
      }
    },
    {
      "condition": "minecraft:entity_properties",
      "entity": "this",
      "predicate": {
        "equipment": {
          "mainhand": {
            "item": "minecraft:stone_sword"
          }
        }
      }
    },
    {
      "condition": "minecraft:entity_properties",
      "entity": "this",
      "predicate": {
        "equipment": {
          "mainhand": {
            "item": "minecraft:golden_sword"
          }
        }
      }
    },
    {
      "condition": "minecraft:entity_properties",
      "entity": "this",
      "predicate": {
        "equipment": {
          "mainhand": {
            "item": "minecraft:iron_sword"
          }
        }
      }
    },
    {
      "condition": "minecraft:entity_properties",
      "entity": "this",
      "predicate": {
        "equipment": {
          "mainhand": {
            "item": "minecraft:diamond_sword"
          }
        }
      }
    },
    {
      "condition": "minecraft:entity_properties",
      "entity": "this",
      "predicate": {
        "equipment": {
          "mainhand": {
            "item": "minecraft:netherite_sword"
          }
        }
      }
    },
    {
      "condition": "minecraft:entity_properties",
      "entity": "this",
      "predicate": {
        "equipment": {
          "mainhand": {
            "item": "minecraft:wooden_axe"
          }
        }
      }
    },
    {
      "condition": "minecraft:entity_properties",
      "entity": "this",
      "predicate": {
        "equipment": {
          "mainhand": {
            "item": "minecraft:stone_axe"
          }
        }
      }
    },
    {
      "condition": "minecraft:entity_properties",
      "entity": "this",
      "predicate": {
        "equipment": {
          "mainhand": {
            "item": "minecraft:golden_axe"
          }
        }
      }
    },
    {
      "condition": "minecraft:entity_properties",
      "entity": "this",
      "predicate": {
        "equipment": {
          "mainhand": {
            "item": "minecraft:iron_axe"
          }
        }
      }
    },
    {
      "condition": "minecraft:entity_properties",
      "entity": "this",
      "predicate": {
        "equipment": {
          "mainhand": {
            "item": "minecraft:diamond_axe"
          }
        }
      }
    },
    {
      "condition": "minecraft:entity_properties",
      "entity": "this",
      "predicate": {
        "equipment": {
          "mainhand": {
            "item": "minecraft:netherite_axe"
          }
        }
      }
    }
  ]
}