{
  "type": "crafting_shapeless",
  "ingredients": [
    {
      "item": "minecraft:chiseled_stone_bricks"
    },
    {
      "item": "minecraft:crafting_table"
    },
    {
      "item": "minecraft:diamond_boots"
    },
    {
      "item": "minecraft:flower_pot"
    },
    {
      "item": "minecraft:glistering_melon_slice"
    },
    {
      "item": "minecraft:light_blue_stained_glass_pane"
    },
    {
      "item": "minecraft:orange_stained_glass"
    },
    {
      "item": "minecraft:sunflower"
    },
    {
      "item": "minecraft:trapped_chest"
    }
  ],
  "result": {
    "item": "minecraft:packed_ice",
    "count": 1
  }
}