{
  "type": "crafting_shapeless",
  "ingredients": [
    {
      "item": "minecraft:beacon"
    },
    {
      "item": "minecraft:cooked_salmon"
    },
    {
      "item": "minecraft:dead_bubble_coral_block"
    },
    {
      "item": "minecraft:light_blue_concrete_powder"
    },
    {
      "item": "minecraft:light_gray_concrete_powder"
    },
    {
      "item": "minecraft:polished_diorite"
    },
    {
      "item": "minecraft:prismarine_brick_stairs"
    },
    {
      "item": "minecraft:sea_lantern"
    },
    {
      "item": "minecraft:yellow_carpet"
    }
  ],
  "result": {
    "item": "minecraft:orange_concrete_powder",
    "count": 1
  }
}