{
  "type": "crafting_shapeless",
  "ingredients": [
    {
      "item": "minecraft:acacia_boat"
    },
    {
      "item": "minecraft:acacia_leaves"
    },
    {
      "item": "minecraft:blue_glazed_terracotta"
    },
    {
      "item": "minecraft:furnace_minecart"
    },
    {
      "item": "minecraft:horn_coral_block"
    },
    {
      "item": "minecraft:magma_block"
    },
    {
      "item": "minecraft:netherrack"
    },
    {
      "item": "minecraft:pink_shulker_box"
    },
    {
      "item": "minecraft:spruce_sapling"
    }
  ],
  "result": {
    "item": "minecraft:purple_concrete_powder",
    "count": 1
  }
}