{
  "type": "crafting_shapeless",
  "ingredients": [
    {
      "item": "minecraft:black_banner"
    },
    {
      "item": "minecraft:conduit"
    },
    {
      "item": "minecraft:golden_chestplate"
    },
    {
      "item": "minecraft:light_blue_concrete"
    },
    {
      "item": "minecraft:light_blue_dye"
    },
    {
      "item": "minecraft:oak_trapdoor"
    },
    {
      "item": "minecraft:oak_wood"
    },
    {
      "item": "minecraft:orange_glazed_terracotta"
    },
    {
      "item": "minecraft:sand"
    }
  ],
  "result": {
    "item": "minecraft:gray_concrete_powder",
    "count": 1
  }
}