{
  "pools": [
    {
      "rolls": 1,
      "entries": [
        {
          "type": "minecraft:item",
          "name": "minecraft:gold_nugget",
          "functions": [
            {
              "function": "minecraft:set_nbt",
              "tag": "{CustomModelData:454,EnchantStone:1b,StoneID:\"進化\",Tier:8,Enchantments:[{id:\"tusb:生命\",lvl:8,Unique:1b}],display:{Name:'{\"translate\":\"進化の宝珠(VIII)\",\"color\":\"aqua\",\"italic\":false}',Lore:['{\"translate\":\"ライフ VIII\",\"color\":\"gray\",\"italic\":false}','{\"translate\":\"マナ VIII\",\"color\":\"gray\",\"italic\":false}','[{\"translate\":\"適用可能アイテム： \",\"color\":\"green\",\"italic\":false},{\"translate\":\"防具\",\"color\":\"gray\"}]']}}"
            }
          ]
        }
      ]
    }
  ]
}