{
  "pools": [
    {
      "rolls": 1,
      "entries": [
        {
          "weight": 16,
          "type": "loot_table",
          "name": "item:item/firework_star/etc/trap_spawn_water_column"
        },
        {
          "weight": 8,
          "type": "loot_table",
          "name": "item:item/firework_star/etc/trap_spawn_mad_urchin"
        },
        {
          "weight": 4,
          "type": "loot_table",
          "name": "item:item/firework_star/etc/trap_spawn_fiend_squid"
        },
        {
          "weight": 4,
          "type": "loot_table",
          "name": "item:item/firework_star/etc/trap_spawn_aqua_dolphin"
        },
        {
          "weight": 1,
          "type": "loot_table",
          "name": "item:item/firework_star/etc/trap_spawn_predator"
        }
      ]
    }
  ]
}